{"id":"2012/05/06","name":"2012/05/06","type":"day","previous":"2012/05/05","next":"2012/05/10","photos":[{"createdTime":"1336323861","images":{"lowResolution":{"url":"http://distilleryimage1.s3.amazonaws.com/860191ba979d11e180c9123138016265_6.jpg","width":306,"height":306},"thumbnail":{"url":"http://distilleryimage1.s3.amazonaws.com/860191ba979d11e180c9123138016265_5.jpg","width":150,"height":150},"standardResolution":{"url":"http://distilleryimage1.s3.amazonaws.com/860191ba979d11e180c9123138016265_7.jpg","width":612,"height":612}},"id":"2012/05/06/185420444542888489_326209","caption":{"createdTime":"1336323865","text":"Sunset Point","from":{"username":"lukekarrys","profilePicture":"http://images.instagram.com/profiles/profile_326209_75sq_1358223211.jpg","id":"326209","fullName":"Luke Karrys"},"id":"185420476771920223"},"likes":{"count":10},"comments":{"count":1}}]}