{"id":"2012/11/11","name":"2012/11/11","type":"day","previous":"2012/11/10","next":"2012/11/12","photos":[{"createdTime":"1352620266","images":{"lowResolution":{"url":"http://distilleryimage8.s3.amazonaws.com/8c9d3f442bd411e2877022000a9f1278_6.jpg","width":306,"height":306},"thumbnail":{"url":"http://distilleryimage8.s3.amazonaws.com/8c9d3f442bd411e2877022000a9f1278_5.jpg","width":150,"height":150},"standardResolution":{"url":"http://distilleryimage8.s3.amazonaws.com/8c9d3f442bd411e2877022000a9f1278_7.jpg","width":612,"height":612}},"id":"2012/11/11/322124602166930324_326209","caption":{"createdTime":"1352620293","text":"On the road","from":{"username":"lukekarrys","profilePicture":"http://images.instagram.com/profiles/profile_326209_75sq_1358223211.jpg","id":"326209","fullName":"Luke Karrys"},"id":"322124830773275514"},"likes":{"count":0},"comments":{"count":0}},{"createdTime":"1352619678","images":{"lowResolution":{"url":"http://distilleryimage1.s3.amazonaws.com/2dc552962bd311e29cc822000a1f96e3_6.jpg","width":306,"height":306},"thumbnail":{"url":"http://distilleryimage1.s3.amazonaws.com/2dc552962bd311e29cc822000a1f96e3_5.jpg","width":150,"height":150},"standardResolution":{"url":"http://distilleryimage1.s3.amazonaws.com/2dc552962bd311e29cc822000a1f96e3_7.jpg","width":612,"height":612}},"id":"2012/11/11/322119664347048829_326209","caption":{"createdTime":"1352619679","text":"On the fence","from":{"username":"lukekarrys","profilePicture":"http://images.instagram.com/profiles/profile_326209_75sq_1358223211.jpg","id":"326209","fullName":"Luke Karrys"},"id":"322119679941471044"},"likes":{"count":1},"comments":{"count":0}},{"createdTime":"1352619020","images":{"lowResolution":{"url":"http://distilleryimage9.s3.amazonaws.com/a5f618e22bd111e2a33422000a1cbd24_6.jpg","width":306,"height":306},"thumbnail":{"url":"http://distilleryimage9.s3.amazonaws.com/a5f618e22bd111e2a33422000a1cbd24_5.jpg","width":150,"height":150},"standardResolution":{"url":"http://distilleryimage9.s3.amazonaws.com/a5f618e22bd111e2a33422000a1cbd24_7.jpg","width":612,"height":612}},"id":"2012/11/11/322114150120745817_326209","caption":{"createdTime":"1352619062","text":"Cold late night bike clothing #30degrees","from":{"username":"lukekarrys","profilePicture":"http://images.instagram.com/profiles/profile_326209_75sq_1358223211.jpg","id":"326209","fullName":"Luke Karrys"},"id":"322114500923943678"},"likes":{"count":8},"comments":{"count":1}}]}