{"id":"2012/07/10","name":"2012/07/10","type":"day","previous":"2012/07/08","next":"2012/07/13","photos":[{"createdTime":"1341970396","images":{"lowResolution":{"url":"http://distilleryimage3.s3.amazonaws.com/634bae06caf811e1aaec22000a1e88af_6.jpg","width":306,"height":306},"thumbnail":{"url":"http://distilleryimage3.s3.amazonaws.com/634bae06caf811e1aaec22000a1e88af_5.jpg","width":150,"height":150},"standardResolution":{"url":"http://distilleryimage3.s3.amazonaws.com/634bae06caf811e1aaec22000a1e88af_7.jpg","width":612,"height":612}},"id":"2012/07/10/232787015397206463_326209","caption":{"createdTime":"1341970401","text":"Storm cloud","from":{"username":"lukekarrys","profilePicture":"http://images.instagram.com/profiles/profile_326209_75sq_1358223211.jpg","id":"326209","fullName":"Luke Karrys"},"id":"232787060603415038"},"likes":{"count":10},"comments":{"count":1}},{"createdTime":"1341926107","images":{"lowResolution":{"url":"http://distilleryimage0.s3.amazonaws.com/44d16068ca9111e1abd612313810100a_6.jpg","width":306,"height":306},"thumbnail":{"url":"http://distilleryimage0.s3.amazonaws.com/44d16068ca9111e1abd612313810100a_5.jpg","width":150,"height":150},"standardResolution":{"url":"http://distilleryimage0.s3.amazonaws.com/44d16068ca9111e1abd612313810100a_7.jpg","width":612,"height":612}},"id":"2012/07/10/232415489871243588_326209","caption":{"createdTime":"1341926148","text":"Possibly my first Instagram sunrise #tooearly","from":{"username":"lukekarrys","profilePicture":"http://images.instagram.com/profiles/profile_326209_75sq_1358223211.jpg","id":"326209","fullName":"Luke Karrys"},"id":"232415835280566478"},"likes":{"count":3},"comments":{"count":0}}]}